{"version":1,"resource":"vscode-remote://970-cs-e7bad38b-3936-4e5f-80b8-5c1139a5a8cd.cs-us-west1-wolo.cloudshell.dev/home/efarzad22/programming1/problem4.c","entries":[{"id":"I4kM.c","timestamp":1757901550930},{"id":"Rwbw.c","timestamp":1757901566821},{"id":"tc8Z.c","timestamp":1757901595628},{"id":"M2tM.c","timestamp":1757901630841},{"id":"DdCe.c","timestamp":1757901641236},{"id":"Rq9w.c","timestamp":1757901702408},{"id":"wExE.c","timestamp":1757901724766},{"id":"11nk.c","timestamp":1757901759124},{"id":"oqIN.c","source":"Workspace Edit","timestamp":1757901851705},{"id":"SD2H.c","timestamp":1757902228175},{"id":"tON6.c","timestamp":1757902242073},{"id":"wBAS.c","timestamp":1757902253509},{"id":"LMOX.c","timestamp":1757902267991},{"id":"O2WI.c","timestamp":1757902296548},{"id":"hnZ3.c","timestamp":1757902397274},{"id":"UihL.c","timestamp":1757902482395},{"id":"vJpF.c","timestamp":1757903044740},{"id":"g1pI.c","timestamp":1757903144009},{"id":"fIOC.c","source":"Workspace Edit","timestamp":1757903186577},{"id":"3N89.c","timestamp":1757903227177},{"id":"fJFi.c","timestamp":1757903272431},{"id":"MelC.c","source":"undoRedo.source","timestamp":1757903276537},{"id":"XAeM.c","timestamp":1757903285131},{"id":"Uyt0.c","timestamp":1757903305309},{"id":"SrLS.c","timestamp":1757903321905},{"id":"Pkft.c","timestamp":1757903341509},{"id":"LJnW.c","timestamp":1757903358042},{"id":"RU6C.c","timestamp":1757903402463},{"id":"aaKE.c","timestamp":1757903431449}]}